{"assets/allDone.png":["assets/allDone.png"],"assets/allDoneDark.png":["assets/allDoneDark.png"],"assets/apple.png":["assets/apple.png"],"assets/cloudScout.png":["assets/cloudScout.png"],"assets/cloudScoutDark.png":["assets/cloudScoutDark.png"],"assets/darkIcon.png":["assets/darkIcon.png"],"assets/darkMail.png":["assets/darkMail.png"],"assets/darkMode.png":["assets/darkMode.png"],"assets/dg4x.png":["assets/dg4x.png"],"assets/disabled.png":["assets/disabled.png"],"assets/enabled.png":["assets/enabled.png"],"assets/google.png":["assets/google.png"],"assets/lg4x.png":["assets/lg4x.png"],"assets/lightMode.png":["assets/lightMode.png"],"assets/lottie/setup-match-notifs.json":["assets/lottie/setup-match-notifs.json"],"assets/mail.png":["assets/mail.png"],"assets/onboardingHome.png":["assets/onboardingHome.png"],"assets/onboardingHomeDark.png":["assets/onboardingHomeDark.png"],"assets/onboardingMyTeam.png":["assets/onboardingMyTeam.png"],"assets/onboardingMyTeamDark.png":["assets/onboardingMyTeamDark.png"],"assets/onboardingRankings.png":["assets/onboardingRankings.png"],"assets/onboardingRankingsDark.png":["assets/onboardingRankingsDark.png"],"assets/onboardingSchedule.png":["assets/onboardingSchedule.png"],"assets/onboardingScheduleDark.png":["assets/onboardingScheduleDark.png"],"assets/radio_button_checked.png":["assets/radio_button_checked.png"],"assets/radio_button_unchecked.png":["assets/radio_button_unchecked.png"],"assets/system.png":["assets/system.png"],"assets/tournamentMode.png":["assets/tournamentMode.png"],"fonts/Manrope-Bold.ttf":["fonts/Manrope-Bold.ttf"],"fonts/Manrope-ExtraBold.ttf":["fonts/Manrope-ExtraBold.ttf"],"fonts/Manrope-Light.ttf":["fonts/Manrope-Light.ttf"],"fonts/Manrope-Medium.ttf":["fonts/Manrope-Medium.ttf"],"fonts/Manrope-Regular.ttf":["fonts/Manrope-Regular.ttf"],"fonts/Manrope-SemiBold.ttf":["fonts/Manrope-SemiBold.ttf"],"packages/cupertino_icons/assets/CupertinoIcons.ttf":["packages/cupertino_icons/assets/CupertinoIcons.ttf"]}